MANIFEST.in
README.rst
setup.cfg
setup.py
docs/index.rst
echafaudage/__init__.py
echafaudage/_looper.py
echafaudage/compat3.py
echafaudage/docopt.py
echafaudage/main.py
echafaudage/tempita.py
echafaudage.egg-info/PKG-INFO
echafaudage.egg-info/SOURCES.txt
echafaudage.egg-info/dependency_links.txt
echafaudage.egg-info/entry_points.txt
echafaudage.egg-info/not-zip-safe
echafaudage.egg-info/top_level.txt