Metadata-Version: 1.1
Name: echafaudage
Version: 0.1.0
Summary: A lighting scaffolding python tool without dependencies
Home-page: http://harobed.github.io/echafaudage/
Author: Stephane Klein
Author-email: contact@stephane-klein.info
License: BSD License
Platform: UNKNOWN
Classifier: Development Status :: 5 - Production/Stable
Classifier: Environment :: Console
Classifier: Operating System :: OS Independent
Classifier: Programming Language :: Python :: 2.7
Classifier: Programming Language :: Python :: 2.6
Classifier: Intended Audience :: Developers
Classifier: License :: OSI Approved :: BSD License
